cytobulk/__init__.py
cytobulk/get/__init__.py
cytobulk/get/_counts.py
cytobulk/get/_get_dataset.py
cytobulk/get/_meta.py
cytobulk/plots/__init__.py
cytobulk/plots/_eval_plot.py
cytobulk/plots/_plot.py
cytobulk/preprocessing/__init__.py
cytobulk/preprocessing/_filtering.py
cytobulk/preprocessing/_preprocessing.py
cytobulk/preprocessing/_rpackage.py
cytobulk/preprocessing/_split_he_image.py
cytobulk/preprocessing/cytobulk_preprocessing.R
cytobulk/tools/__init__.py
cytobulk/tools/_deconv.py
cytobulk/tools/_he_inference.py
cytobulk/tools/_mapping.py
cytobulk/tools/_segmentation.py
cytobulk/tools/_st_reconstruction.py
cytobulk/tools/model/__init__.py
cytobulk/tools/model/_graph_deconv.py
cytobulk/tools/model/_he_prediction.py
cytobulk/utils/__init__.py
cytobulk/utils/_evaluation.py
cytobulk/utils/_math.py
cytobulk/utils/_read_data.py
cytobulk/utils/_stimulation.py
cytobulk/utils/_utils.py
CytoBulk-0.1.20.dist-info/LICENSE
CytoBulk-0.1.20.dist-info/METADATA
CytoBulk-0.1.20.dist-info/WHEEL
CytoBulk-0.1.20.dist-info/top_level.txt
CytoBulk-0.1.20.dist-info/RECORD
