Metadata-Version: 2.1
Name: CytoBulk
Version: 0.1.20
Summary: Integrating transcriptional data to decipher the tumor microenvironment with the graph frequency domain model
Home-page: https://github.com/kristaxying/CytoBulk
Author: Xueying WANG
Author-email: your_email@example.com
Classifier: Programming Language :: Python :: 3
Classifier: License :: OSI Approved :: MIT License
Classifier: Operating System :: OS Independent
Requires-Python: >=3.10
License-File: LICENSE
Requires-Dist: anndata >=0.10.0
Requires-Dist: cellpose >=3.0.10
Requires-Dist: imageio
Requires-Dist: matplotlib
Requires-Dist: numpy >=1.23.0
Requires-Dist: openslide-python
Requires-Dist: ortools ==9.3.10497
Requires-Dist: pandas >=2.2.0
Requires-Dist: Pillow
Requires-Dist: POT ==0.9.5
Requires-Dist: rpy2 >=3.5.0
Requires-Dist: scanpy
Requires-Dist: scikit-learn
Requires-Dist: scipy
Requires-Dist: seaborn
Requires-Dist: torch <2.6.0,>2.1.0
Requires-Dist: torchvision
Requires-Dist: tqdm
Requires-Dist: requests
Requires-Dist: openslide-bin
Requires-Dist: scikit-image
Requires-Dist: igraph
Requires-Dist: leidenalg
